aop/__init__.py
aop/exceptions.py
aop/structure.py
aop/api/__init__.py
aop/api/base.py
aop/api/logistics/__init__.py
aop/api/logistics/logistic_company.py
aop/api/logistics/logistics_trace_info.py
aop/api/transaction/__init__.py
aop/api/transaction/trade_buyer_order_list.py
aop/api/transaction/trade_buyer_view.py
aop/api/transaction/trade_fast_create_order.py
aop/api/transaction/trade_receive_address.py
open_1688-0.0.1.dist-info/LICENSE
open_1688-0.0.1.dist-info/METADATA
open_1688-0.0.1.dist-info/WHEEL
open_1688-0.0.1.dist-info/top_level.txt
open_1688-0.0.1.dist-info/RECORD
